pyglodls/__init__.py
pyglodls/glodls.py
pyglodls-0.0.6.dist-info/METADATA
pyglodls-0.0.6.dist-info/WHEEL
pyglodls-0.0.6.dist-info/top_level.txt
pyglodls-0.0.6.dist-info/RECORD
