Metadata-Version: 2.1
Name: pyglodls
Version: 0.0.6
Summary: Python interface to http://glodls.to
Home-page: https://github.com/srob650/pyglodls
Author: srob650
Author-email: pytvmaze@gmail.com
License: MIT
Keywords: python glodls glotorrents torrents torrent
Platform: UNKNOWN
Classifier: Development Status :: 2 - Pre-Alpha
Classifier: Intended Audience :: Developers
Classifier: License :: OSI Approved :: MIT License
Classifier: Programming Language :: Python :: 2.7
Classifier: Programming Language :: Python :: 3.5
Requires-Dist: requests
Requires-Dist: bs4
